<?xml version="1.0" encoding="UTF-8"?>
<metadata xml:lang="en"><Esri><CreaDate>20230126</CreaDate><CreaTime>08585800</CreaTime><ArcGISFormat>1.0</ArcGISFormat><SyncOnce>TRUE</SyncOnce><ModDate>20230210</ModDate><ModTime>093307</ModTime></Esri><toolbox name="Routing" alias="toolbox"><arcToolboxHelpPath>c:\program files\arcgis\pro\Resources\Help\gp</arcToolboxHelpPath><toolsets/></toolbox><dataIdInfo><idCitation><resTitle>Routing</resTitle></idCitation></dataIdInfo><distInfo><distributor><distorFormat><formatName>ArcToolbox Toolbox</formatName></distorFormat></distributor></distInfo></metadata>
